pierex/__init__.py
pierex/pierex.py
pierex-0.1.0.dist-info/METADATA
pierex-0.1.0.dist-info/WHEEL
pierex-0.1.0.dist-info/entry_points.txt
pierex-0.1.0.dist-info/top_level.txt
pierex-0.1.0.dist-info/RECORD
